vc_diss_cruncher.py
vc_diss-1.2.1.dist-info/DESCRIPTION.rst
vc_diss-1.2.1.dist-info/METADATA
vc_diss-1.2.1.dist-info/RECORD
vc_diss-1.2.1.dist-info/WHEEL
vc_diss-1.2.1.dist-info/entry_points.txt
vc_diss-1.2.1.dist-info/metadata.json
vc_diss-1.2.1.dist-info/top_level.txt
