Metadata-Version: 2.0
Name: vc-diss
Version: 1.2.1
Summary: The cruncher app for vc-diss.
Home-page: https://github.com/tdthornton/vc-diss-cruncher
Author: Tom Thornton
Author-email: i7219215@bournemouth.ac.uk
License: MIT
Keywords: sample setuptools development
Platform: UNKNOWN
Classifier: Development Status :: 3 - Alpha
Classifier: Intended Audience :: Developers
Classifier: Topic :: Software Development :: Build Tools
Classifier: License :: OSI Approved :: MIT License
Classifier: Programming Language :: Python :: 2
Classifier: Programming Language :: Python :: 2.7
Classifier: Programming Language :: Python :: 3
Classifier: Programming Language :: Python :: 3.3
Classifier: Programming Language :: Python :: 3.4
Classifier: Programming Language :: Python :: 3.5
